gnuplot_kernel/__init__.py
gnuplot_kernel/__main__.py
gnuplot_kernel/exceptions.py
gnuplot_kernel/kernel.py
gnuplot_kernel/py.typed
gnuplot_kernel/replwrap.py
gnuplot_kernel/statement.py
gnuplot_kernel/utils.py
gnuplot_kernel/images/logo-32x32.png
gnuplot_kernel/images/logo-64x64.png
gnuplot_kernel/images/logo.gp
gnuplot_kernel/magics/__init__.py
gnuplot_kernel/magics/gnuplot_magic.py
gnuplot_kernel/magics/reset_magic.py
gnuplot_kernel-0.5.0.dist-info/licenses/LICENSE
gnuplot_kernel-0.5.0.dist-info/METADATA
gnuplot_kernel-0.5.0.dist-info/WHEEL
gnuplot_kernel-0.5.0.dist-info/top_level.txt
gnuplot_kernel-0.5.0.dist-info/RECORD
