Metadata-Version: 2.4
Name: gnuplot_kernel
Version: 0.5.0
Summary: A gnuplot kernel for Jupyter
Author-email: Hassan Kibirige <has2k1@gmail.com>
License: Copyright (c) 2016, Hassan Kibirige 
Project-URL: homepage, https://github.com/has2k1/gnuplot_kernel
Project-URL: repository, https://github.com/has2k1/gnuplot_kernel
Project-URL: ci, https://github.com/has2k1/gnuplot_kernel/actions
Classifier: Framework :: IPython
Classifier: Intended Audience :: End Users/Desktop
Classifier: Intended Audience :: Science/Research
Classifier: License :: OSI Approved :: BSD License
Classifier: Programming Language :: Python :: 3
Classifier: Topic :: Scientific/Engineering :: Visualization
Classifier: Topic :: System :: Shells
Requires-Python: >=3.10
License-File: LICENSE
Requires-Dist: metakernel>=0.30.0
Requires-Dist: jupyter>=1.1.1
Provides-Extra: dev
Requires-Dist: gnuplot_kernel[test]; extra == "dev"
Requires-Dist: ruff; extra == "dev"
Requires-Dist: matplotlib>=3.8.0; extra == "dev"
Requires-Dist: pyright>=1.1.405; extra == "dev"
Provides-Extra: test
Requires-Dist: pytest-cov>=4.0.0; extra == "test"
Dynamic: license-file
